mcproto/__init__.py
mcproto/buffer.py
mcproto/connection.py
mcproto/encryption.py
mcproto/multiplayer.py
mcproto/py.typed
mcproto/auth/__init__.py
mcproto/auth/account.py
mcproto/auth/msa.py
mcproto/auth/yggdrasil.py
mcproto/auth/microsoft/__init__.py
mcproto/auth/microsoft/oauth.py
mcproto/auth/microsoft/xbox.py
mcproto/packets/__init__.py
mcproto/packets/interactions.py
mcproto/packets/packet.py
mcproto/packets/packet_map.py
mcproto/packets/handshaking/__init__.py
mcproto/packets/handshaking/handshake.py
mcproto/packets/login/__init__.py
mcproto/packets/login/login.py
mcproto/packets/status/__init__.py
mcproto/packets/status/ping.py
mcproto/packets/status/status.py
mcproto/protocol/__init__.py
mcproto/protocol/base_io.py
mcproto/protocol/utils.py
mcproto/types/__init__.py
mcproto/types/abc.py
mcproto/types/chat.py
mcproto/types/nbt.py
mcproto/types/uuid.py
mcproto/utils/__init__.py
mcproto/utils/abc.py
mcproto/utils/deprecation.py
mcproto-0.6.0.dist-info/METADATA
mcproto-0.6.0.dist-info/WHEEL
mcproto-0.6.0.dist-info/licenses/LICENSE-THIRD-PARTY.txt
mcproto-0.6.0.dist-info/licenses/LICENSE.txt
mcproto-0.6.0.dist-info/RECORD
