Metadata-Version: 2.4
Name: mcproto
Version: 0.6.0
Summary: Library providing easy interactions with minecraft servers
Project-URL: Documentation, https://py-mine.github.io/mcproto
Project-URL: Source code, https://github.com/py-mine/mcproto
Author-email: ItsDrike <itsdrike@protonmail.com>
Maintainer-email: ItsDrike <itsdrike@protonmail.com>
License-Expression: LGPL-3.0-or-later
License-File: LICENSE-THIRD-PARTY.txt
License-File: LICENSE.txt
Keywords: minecraft,protocol
Classifier: Development Status :: 2 - Pre-Alpha
Classifier: Intended Audience :: Developers
Classifier: License :: OSI Approved :: GNU Lesser General Public License v3 or later (LGPLv3+)
Classifier: Natural Language :: English
Classifier: Operating System :: OS Independent
Classifier: Programming Language :: Python
Classifier: Programming Language :: Python :: 3
Classifier: Programming Language :: Python :: 3.9
Classifier: Programming Language :: Python :: 3.10
Classifier: Programming Language :: Python :: 3.11
Classifier: Programming Language :: Python :: 3.12
Classifier: Programming Language :: Python :: 3.13
Classifier: Topic :: Games/Entertainment
Classifier: Topic :: Software Development :: Libraries
Classifier: Topic :: Software Development :: Libraries :: Python Modules
Classifier: Topic :: System :: Networking
Classifier: Typing :: Typed
Requires-Python: >=3.9
Requires-Dist: asyncio-dgram>=2.2.0
Requires-Dist: attrs>=25.3.0
Requires-Dist: cryptography>=45.0.5
Requires-Dist: httpx>=0.28.1
Requires-Dist: packaging>=25.0
Requires-Dist: typing-extensions>=4.14.1
